django_pg_ddl_extras/__init__.py
django_pg_ddl_extras/constraints.py
django_pg_ddl_extras/pg_functions.py
django_pg_ddl_extras-0.1.0.dist-info/LICENSE
django_pg_ddl_extras-0.1.0.dist-info/WHEEL
django_pg_ddl_extras-0.1.0.dist-info/METADATA
django_pg_ddl_extras-0.1.0.dist-info/RECORD
