Metadata-Version: 2.1
Name: django-pg-ddl-extras
Version: 0.1.0
Summary: Postgres declarative functions for Django
License: MIT
Author: Jerome Leclanche
Author-email: jerome@leclan.ch
Requires-Python: >=3.7
Classifier: License :: OSI Approved :: MIT License
Classifier: Programming Language :: Python :: 3
Classifier: Programming Language :: Python :: 3.7
Classifier: Programming Language :: Python :: 3.8
Classifier: Programming Language :: Python :: 3.9
Classifier: Programming Language :: Python :: 3.10
Requires-Dist: Django (>=3.2)
